aicv/__init__.py
aicv/main.py
aicv/utils/__init__.py
aicv/utils/remove_background.py
aicv/utils/separator.py
aicv/utils/yolo_generator.py
ai_cv_utils-0.0.6.dist-info/LICENSE
ai_cv_utils-0.0.6.dist-info/METADATA
ai_cv_utils-0.0.6.dist-info/WHEEL
ai_cv_utils-0.0.6.dist-info/entry_points.txt
ai_cv_utils-0.0.6.dist-info/top_level.txt
ai_cv_utils-0.0.6.dist-info/RECORD
