Metadata-Version: 2.1
Name: ai-cv-utils
Version: 0.0.6
Summary: AI Computer Vision Utilities
Home-page: https://github.com/gbertolani/ai-cv-utils
Author: Gaston Alberto Bertolani
Author-email: gbertolani.in@gmail.com
License: AGPL3+
Platform: UNKNOWN
Classifier: Programming Language :: Python :: 3
Classifier: Operating System :: OS Independent
Classifier: Topic :: Utilities
Requires-Python: >=3.6
License-File: LICENSE
Requires-Dist: cycler
Requires-Dist: kiwisolver
Requires-Dist: matplotlib
Requires-Dist: numpy
Requires-Dist: opencv-python-headless
Requires-Dist: Pillow
Requires-Dist: pyparsing
Requires-Dist: python-dateutil
Requires-Dist: six
Requires-Dist: click
